simple_dnn/Classes.py
simple_dnn/__init__.py
easy_dnn-0.0.1.dist-info/LICENSE
easy_dnn-0.0.1.dist-info/METADATA
easy_dnn-0.0.1.dist-info/WHEEL
easy_dnn-0.0.1.dist-info/top_level.txt
easy_dnn-0.0.1.dist-info/RECORD
