Metadata-Version: 2.1
Name: easy-dnn
Version: 0.0.1
Summary: An easy way to show how a simple deep neural net outperforms a logistic regression classifier.
Home-page: https://github.com/yishairasowsky/nn_vs_log_reg
Author: Yishai Rasowsky
Author-email: yishairasowsky@gmail.com
License: UNKNOWN
Platform: UNKNOWN
Classifier: Programming Language :: Python :: 3
Classifier: License :: OSI Approved :: MIT License
Classifier: Operating System :: OS Independent
Requires-Python: >=3.6
